[
	{
		"name": "Sacred Lake",
		"uniqueTo": "Bamboo Kingdom",
		"gold": 1,
		"food": 1,
		"terrainsCanBeBuiltOn": ["Hill"],
		"turnsToBuild": 14,
		"uniques": ["Great Improvement", "[-2 Production]", "[+2 Culture, +2 Faith] for each adjacent [City center]", "[+1 Food] from [Fresh water] tiles <after discovering [Civil Service]>",	"Cannot be built on [Hill] tiles <with [1] to [6] neighboring [Sacred Lake] tiles>"],
		"techRequired": "Construction",
		"shortcutKey": "M"
	},
		 {
        "name": "Skynet",
        "uniqueTo": "Penguinesia",
        "terrainsCanBeBuiltOn": ["Coast","Ocean"]
        "food": 1,
        "culture": 1,
        "turnsToBuild": 5,
        "techRequired": "Optics",
        "uniques": [
            "[+1 Production] <after discovering [Navigation]>",
            "[+1 Culture] <after discovering [Flight]>",
            "Cannot be built on [resource] tiles",
            "Pillaging this improvement yields approximately [+20 Gold]"
        ]
    },
	{
		"name": "Pineapple Plantation",		
        "uniqueTo": "Sylvanor",
		"terrainsCanBeBuiltOn": ["Jungle"],
		"gold": 2,
		"turnsToBuild": 7,
		"techRequired": "Calendar",
		"uniques": [
				"Provides [1] [Pineapple]",
				"[+1 Food] <after discovering [Fertilizer]>",
				"Cannot be built on [Bonus resource] tiles", 
				"Cannot be built on [Luxury resource] tiles",
				"Does not need removal of [Jungle]"]
	},
	// Unique Choices
	{
		"name": "UI 1",
		"terrainsCanBeBuiltOn": ["Land"],
		"uniques": ["Will not be displayed in Civilopedia", "Unbuildable"]
	},
	{
		"name": "UI 2",
		"terrainsCanBeBuiltOn": ["Land"],
		"uniques": ["Will not be displayed in Civilopedia", "Unbuildable"]
	},
	{
		"name": "UI 3",
		"terrainsCanBeBuiltOn": ["Land"],
		"uniques": ["Will not be displayed in Civilopedia", "Unbuildable"]
	},
	{
		"name": "UI 4",
		"terrainsCanBeBuiltOn": ["Land"],
		"uniques": ["Will not be displayed in Civilopedia", "Unbuildable"]
	},
	{
		"name": "UI 5",
		"terrainsCanBeBuiltOn": ["Land"],
		"uniques": ["Will not be displayed in Civilopedia", "Unbuildable"]
	},
	{
		"name": "UI 6",
		"terrainsCanBeBuiltOn": ["Land"],
		"uniques": ["Will not be displayed in Civilopedia", "Unbuildable"]
	},
	{
		"name": "UI 7",
		"terrainsCanBeBuiltOn": ["Land"],
		"uniques": ["Will not be displayed in Civilopedia", "Unbuildable"]
	},
	{
		"name": "UI 8",
		"terrainsCanBeBuiltOn": ["Land"],
		"uniques": ["Will not be displayed in Civilopedia", "Unbuildable"]
	},
	{
		"name": "UI 9",
		"terrainsCanBeBuiltOn": ["Land"],
		"uniques": ["Will not be displayed in Civilopedia", "Unbuildable"]
	},
	{
		"name": "UI 10",
		"terrainsCanBeBuiltOn": ["Land"],
		"uniques": ["Will not be displayed in Civilopedia", "Unbuildable"]
	},
]
